tracker/__init__.py
tracker/centroidtracker.py
centroid_tracker-0.0.8.dist-info/METADATA
centroid_tracker-0.0.8.dist-info/WHEEL
centroid_tracker-0.0.8.dist-info/top_level.txt
centroid_tracker-0.0.8.dist-info/RECORD
